torchforge/__init__.py
torchforge-0.0.1.dist-info/METADATA
torchforge-0.0.1.dist-info/WHEEL
torchforge-0.0.1.dist-info/top_level.txt
torchforge-0.0.1.dist-info/RECORD
