Metadata-Version: 2.4
Name: torchforge
Version: 0.0.1
Summary: LLM post training at scale in native PyTorch
Author-email: PyTorch Team <packages@pytorch.org>
